Workbook

Sheet INPUTS
A1: Step 1 | B1: Save a copy of this sheet in the relevant folder. Make sure it is dated correctly
A2: Step 2 | B2: Import all data into all sheets coloured green. Parameters require Column B ONLY to complete the bill. Do NOT leave gaps
A3: Step 3 | B3: Under 'Developer' -> 'Macros' -> Run 'BillingGeneration'
A4: Step 4 | B4: Find Bill output under 'Bill' sheet

Sheet Parameters
A1: Client Name | B1: xxx
A2: Currency | B2: GBP
A3: Exchange Rate
A4: Billing Period Start Date
A5: Billing Period End Date
A6: Billing Frequency
A7: Client PO Number
A8: Payment Terms | B8: 30 days
A9: Instruction Number
A10: Prev Bil Date
A11: Next Bill Date
A12: Scope
A13: VAT Applied?
A14: Person to be billed
A15: Annual Charge per lease | B15: 0

Sheet Payable (HLSELIST)
A1: Lease Payable | B1: Property Name | C1: Reconciliation Ind | D1: Lease Payable Description | E1: Type | F1: Landlord Ref | G1: Landlord Name | H1: Property Ref | I1: Lease Start Date | J1: Lease Expiry Date | K1: Status | L1: Alerts | M1: Transactions | N1: Passing Rent | O1: Document Language Code | P1: Document Language | Q1: Map

Sheet Receivable (LEASELIST)
A1: Lease | B1: Lease Description | C1: Reconciliation Ind | D1: Collection ID | E1: Type | F1: Tenant Ref | G1: Tenant Name | H1: Property Ref | I1: Lease Start Date | J1: Lease Expiry Date | K1: Passing Rent | L1: Status | M1: Alerts | N1: Transactions

Sheet Freehold (PROPLIST)
A1: Property | B1: Property Name | C1: Address Line 1 | D1: Manager Name | E1: Type | F1: ERV | G1: Passing Rent (REC) | H1: Passing Rent (PAY) | I1: Alerts | J1: Planner | K1: Public Holiday | L1: Map

Sheet Prev Period Master
A1: LeaseID | B1: Description/Property Name

Sheet OUTPUTS

Sheet New Period Master
A1: LeaseID | B1: Description/Property Name

Sheet Summary
A1: Prev Bill data from Dec 2024 report
A2: Count Payable | B2: {=SUMPRODUCT(--(LEFT('Prev Period Master'!A:A,2)="24"))} -> 0
A3: Count Receivable | B3: {=SUMPRODUCT(--(LEFT('Prev Period Master'!A:A,2)="18"))} -> 0
A4: Count Freehold/Blank | B4: {=SUMPRODUCT(--(LEFT('Prev Period Master'!A:A,2)="15"))} -> 0
A5: Total | B5: =SUM(B2:B4) -> 0
A7: Current Bill Summary
A8: Count Payable | B8: =SUMPRODUCT(--(LEFT('New Period Master'!A2:A42,2)="24")) -> 0
A9: Count Receivable | B9: =SUMPRODUCT(--(LEFT('New Period Master'!A2:A42,2)="18")) -> 0
A10: Count Freehold | B10: =SUMPRODUCT(--(LEFT('New Period Master'!A2:A42,2)="15")) -> 0
A11: Total - chargeable | B11: =SUM(B8:B9) -> 0
A14: Changes in MRI
A15: Count Terminated | B15: =COUNTIF('Prev Period Master'!#REF!,"Terminated") -> #REF!
A16: Count Abstracted | B16: =COUNTIF('New Period Master'!#REF!,"Abstracted") -> #REF!
A17: xChange since last bill | B17: =B16-B15 -> #REF!

Sheet Bill
E1: Payment Terms | F1: =Parameters!B8 -> 30 days
B2: =Parameters!B1 -> xxx | E2: Instruction number | F2: =Parameters!B9 -> 0
B3: Currency | C3: =Parameters!B2 -> GBP | E3: Previous Bill Date | F3: =Parameters!B10 -> 0
B4: Exchange Rate | C4: =IF(Parameters!B3=0,"",Parameters!B3) | E4: Next Bill Date | F4: =Parameters!B11 -> 0
B5: Billing Period | C5: =TEXT(Parameters!B4,"d mmmm yyyy") & " - " & TEXT(Parameters!B5," d mmmm yyyy") -> 0 January 1900 - 0 January 1900 | E5: Scope | F5: =IF(Parameters!B12=0,"",Parameters!B12)
B6: Billing Frequency | C6: =Parameters!B6 -> 0 | E6: VAT applied? | F6: =IF(Parameters!B13=0,"",Parameters!B13)
B7: Client PO Number | C7: =IF(Parameters!B7=0,"",Parameters!B7) | E7: Person to be billed | F7: =IF(Parameters!B14=0,"",Parameters!B14)
B10: Notes | C10: Database Management Fee | D10: Number of Contracts | E10: Annual Charge Per Contract (GBP) | F10: Net Fee For Period | G10: VAT @ 20% | H10: Total Fee (GBP)
B11: Cost of MRI PLE Database increases by £750.00 p/a per 50 leased locations / owned sites | C11: ="Charged @ "&Parameters!B15&" GBP per lease / p.a " -> Charged @ 0 GBP per lease / p.a | D11: =Summary!$B$11 -> 0 | E11: =Parameters!B15 -> 0 | F11: =(E11*D11)*((Parameters!B5-Parameters!B4+1)/365) -> 0 | G11: =F11*20% -> 0 | H11: =G11+F11 -> 0
C12: Annual MRI ProLease Enterprise Database fee | D12: =Summary!$B$11 -> 0 | E12: n/a | G12: =F12*20% -> 0 | H12: =G12+F12 -> 0
C13: Full reporting package | D13: =Summary!$B$11 -> 0 | E13: 0 | G13: 0 | H13: =G13+F13 -> 0
E14: Total | F14: =SUM(F11:F13) -> 0 | G14: =SUM(G11:G13) -> 0 | H14: =SUM(H11:H13) -> 0
B16: New Abstractions Completed
B17: System ID | C17: Property Name | D17: Number of Contracts | E17: Charge Per Contract (GBP) | F17: Net Fee | G17: VAT @ 20% | H17: Total Fee (GBP)
